tvb_data/__init__.py
tvb_data/brco/tvb-brco.xml
tvb_data/connectivity/__init__.py
tvb_data/connectivity/connectivity_192.zip
tvb_data/connectivity/connectivity_66.zip
tvb_data/connectivity/connectivity_68.zip
tvb_data/connectivity/connectivity_76.zip
tvb_data/connectivity/connectivity_96.zip
tvb_data/connectivity/paupau.zip
tvb_data/dti_pipeline_toronto/output_ConnectionCapacityMatrix.csv
tvb_data/dti_pipeline_toronto/output_ConnectionDistanceMatrix.csv
tvb_data/gifti/__init__.py
tvb_data/gifti/sample.cortex.gii
tvb_data/local_connectivity/__init__.py
tvb_data/local_connectivity/local_connectivity_16384.mat
tvb_data/obj/__init__.py
tvb_data/obj/eeg_cap.obj
tvb_data/obj/face_surface.obj
tvb_data/projectionMatrix/__init__.py
tvb_data/projectionMatrix/projection_eeg_62_surface_16k.mat
tvb_data/projectionMatrix/projection_eeg_65_surface_16k.npy
tvb_data/projectionMatrix/projection_meg_276_surface_16k.npy
tvb_data/regionMapping/__init__.py
tvb_data/regionMapping/regionMapping_16k_192.txt
tvb_data/regionMapping/regionMapping_16k_76.txt
tvb_data/sensors/__init__.py
tvb_data/sensors/eeg_brainstorm_65.txt
tvb_data/sensors/eeg_unitvector_62.txt.bz2
tvb_data/sensors/meg_151.txt.bz2
tvb_data/sensors/meg_brainstorm_276.txt
tvb_data/sensors/seeg_39.txt.bz2
tvb_data/sensors/seeg_588.txt
tvb_data/surfaceData/__init__.py
tvb_data/surfaceData/cortex_16384.zip
tvb_data/surfaceData/face_8614.zip
tvb_data/surfaceData/inner_skull_4096.zip
tvb_data/surfaceData/outer_skin_4096.zip
tvb_data/surfaceData/outer_skull_4096.zip
tvb_data/surfaceData/scalp_1082.zip
tvb_data-3.0.0.dist-info/METADATA
tvb_data-3.0.0.dist-info/WHEEL
tvb_data-3.0.0.dist-info/licenses/LICENSE
tvb_data-3.0.0.dist-info/RECORD
