Metadata-Version: 2.4
Name: tvb-data
Version: 3.0.0
Summary: A package with data for TVB
Project-URL: Homepage, http://www.thevirtualbrain.org
Project-URL: Download, https://gitlab.ebrains.eu/ri/tech-hub/apps/tvb/tvb-data
Author-email: TVB Team <tvb.admin@thevirtualbrain.org>
License: TheVirtualBrain is a brain-simulation software. See also http://www.thevirtualbrain.org
License-File: LICENSE
Keywords: animal,brain,data,delay,dynamics,human,models,neuronal,neuroscience,simulator,tvb
Requires-Python: >=3.8
